opengemini_client_python_application/__init__.py
opengemini_client_python_application-0.0.7.dist-info/licenses/LICENSE
opengemini_client_python_application-0.0.7.dist-info/licenses/NOTICE
opengemini_client_python_application-0.0.7.dist-info/METADATA
opengemini_client_python_application-0.0.7.dist-info/WHEEL
opengemini_client_python_application-0.0.7.dist-info/top_level.txt
opengemini_client_python_application-0.0.7.dist-info/RECORD
