Metadata-Version: 2.4
Name: opengemini-client-python-application
Version: 0.0.7
Project-URL: Homepage, https://github.com/git-org-name/git-repo-name
Project-URL: Repository, https://github.com/git-org-name/git-repo-name
Project-URL: Documentation, https://github.com/git-org-name/git-repo-name#readme
Requires-Python: >=3.9
License-File: LICENSE
License-File: NOTICE
Requires-Dist: blockcontent>=0.2.0
Requires-Dist: flyway>=0.1.0
Requires-Dist: langchain-community>=0.4.1
Requires-Dist: langchain>=1.1.0
Requires-Dist: mcp-protocol>=0.1.0
Requires-Dist: opendal>=0.46.0
Requires-Dist: opengemini-client>=0.1.0
Dynamic: license-file
